rethink/Core.py
rethink/__init__.py
rethink_core-0.1.1.dist-info/licenses/LICENSE
rethink_core-0.1.1.dist-info/METADATA
rethink_core-0.1.1.dist-info/WHEEL
rethink_core-0.1.1.dist-info/entry_points.txt
rethink_core-0.1.1.dist-info/top_level.txt
rethink_core-0.1.1.dist-info/RECORD
