Metadata-Version: 2.4
Name: rethink-core
Version: 0.1.1
Summary: Rethink Core module package
Author-email: fiandev <fiandev1234@gmail.com>
License-File: LICENSE
Provides-Extra: dev
Requires-Dist: pytest; extra == "dev"
Dynamic: license-file
